setup.py
chatglm_cli.egg-info/PKG-INFO
chatglm_cli.egg-info/SOURCES.txt
chatglm_cli.egg-info/dependency_links.txt
chatglm_cli.egg-info/entry_points.txt
chatglm_cli.egg-info/not-zip-safe
chatglm_cli.egg-info/requires.txt
chatglm_cli.egg-info/top_level.txt
chatglmcli/__init__.py
chatglmcli/cmd.py