Metadata-Version: 2.1
Name: chatglm-cli
Version: 0.0.1
Summary: chatglm llm cli
Home-page: https://github.com/xxx
Author: auth
Author-email: xxx@gmail.com
License: MIT
Platform: UNKNOWN
